odoo9_addon_sale_revert_done-9.0.1.0.0.99.dev7-py3.8-nspkg.pth
odoo_addons/sale_revert_done/README.rst
odoo_addons/sale_revert_done/__init__.py
odoo_addons/sale_revert_done/__openerp__.py
odoo_addons/sale_revert_done/i18n/ca.po
odoo_addons/sale_revert_done/i18n/de.po
odoo_addons/sale_revert_done/i18n/el_GR.po
odoo_addons/sale_revert_done/i18n/es.po
odoo_addons/sale_revert_done/i18n/es_ES.po
odoo_addons/sale_revert_done/i18n/es_VE.po
odoo_addons/sale_revert_done/i18n/fi.po
odoo_addons/sale_revert_done/i18n/fr.po
odoo_addons/sale_revert_done/i18n/hr.po
odoo_addons/sale_revert_done/i18n/hr_HR.po
odoo_addons/sale_revert_done/i18n/hu.po
odoo_addons/sale_revert_done/i18n/it.po
odoo_addons/sale_revert_done/i18n/nl.po
odoo_addons/sale_revert_done/i18n/nl_NL.po
odoo_addons/sale_revert_done/i18n/pt.po
odoo_addons/sale_revert_done/i18n/pt_BR.po
odoo_addons/sale_revert_done/i18n/ro.po
odoo_addons/sale_revert_done/i18n/sale_revert_done.pot
odoo_addons/sale_revert_done/i18n/sk.po
odoo_addons/sale_revert_done/i18n/sl.po
odoo_addons/sale_revert_done/i18n/tr.po
odoo_addons/sale_revert_done/i18n/tr_TR.po
odoo_addons/sale_revert_done/i18n/vi_VN.po
odoo_addons/sale_revert_done/i18n/zh_CN.po
odoo_addons/sale_revert_done/models/__init__.py
odoo_addons/sale_revert_done/models/sale_order.py
odoo_addons/sale_revert_done/static/description/icon.png
odoo_addons/sale_revert_done/views/sale_revert_done_view.xml
odoo9_addon_sale_revert_done-9.0.1.0.0.99.dev7.dist-info/METADATA
odoo9_addon_sale_revert_done-9.0.1.0.0.99.dev7.dist-info/WHEEL
odoo9_addon_sale_revert_done-9.0.1.0.0.99.dev7.dist-info/namespace_packages.txt
odoo9_addon_sale_revert_done-9.0.1.0.0.99.dev7.dist-info/top_level.txt
odoo9_addon_sale_revert_done-9.0.1.0.0.99.dev7.dist-info/RECORD
